LICENSE
MANIFEST.in
README.rst
compat.cpp
example.py
gen_enums.py
setup.py
glsl-parser/.git
glsl-parser/EXAMPLE_ERRORS.md
glsl-parser/LICENSE
glsl-parser/Makefile
glsl-parser/README.md
glsl-parser/ast.cpp
glsl-parser/ast.h
glsl-parser/lexemes.h
glsl-parser/lexer.cpp
glsl-parser/lexer.h
glsl-parser/main.cpp
glsl-parser/parser.cpp
glsl-parser/parser.h
glsl-parser/test.py
glsl-parser/util.cpp
glsl-parser/util.h
pyglsl_parser/__init__.py
pyglsl_parser/ast.py
pyglsl_parser/enums.py
pyglsl_parser/lexemes.py
pyglsl_parser/parser.cpp
pyglsl_parser/parser.pyx
pyglsl_parser.egg-info/PKG-INFO
pyglsl_parser.egg-info/SOURCES.txt
pyglsl_parser.egg-info/dependency_links.txt
pyglsl_parser.egg-info/top_level.txt
test/test_parser.py