Metadata-Version: 1.0
Name: pyglsl-parser
Version: 0.6.2
Summary: Python wrapper around glsl-parser
Home-page: https://github.com/nicholasbishop/pyglsl_parser
Author: Nicholas Bishop
Author-email: nicholasbishop@gmail.com
License: UNKNOWN
Platform: UNKNOWN
